spi_slave_8lane.v
/*
 * 8-Lane Parallel SPI Slave Receiver
 *
 * Receives 128-bit data over 8 parallel data lines.
 * - Samples data on rising edge of external SPI clock
 * - Handles clock domain crossing (async spi_clk to system clk)
 * - Raises interrupt when 16 bytes (128 bits) received
 * - Little-endian byte order (LSB first)
 */

module spi_slave_8lane (
    // System interface
    input  wire        clk,           // System clock
    input  wire        resetn,        // Active-low reset

    // SPI Slave interface (directly from external master)
    input  wire        spi_clk_in,    // SPI clock from remote master
    input  wire [7:0]  spi_data_in,   // 8-lane parallel data input
    input  wire        spi_cs_n_in,   // Chip select (active low)

    // Output interface
    output reg  [127:0] rx_data,      // Received 128-bit data
    output reg         rx_valid,      // Pulses high for 1 cycle when complete
    output wire        rx_busy,       // High during active reception
    output wire        irq_rx         // Directly connects to CPU interrupt
);

    // =========================================================================
    // State Machine States
    // =========================================================================
    localparam STATE_IDLE      = 2'b00;
    localparam STATE_RECEIVING = 2'b01;
    localparam STATE_COMPLETE  = 2'b10;

    reg [1:0] state, state_next;

    // =========================================================================
    // Clock Domain Crossing - Synchronize async SPI signals to system clock
    // =========================================================================

    // Double-flop synchronizers for SPI clock
    reg spi_clk_sync1, spi_clk_sync2, spi_clk_sync3;

    // Double-flop synchronizers for chip select
    reg spi_cs_n_sync1, spi_cs_n_sync2;

    // Double-flop synchronizers for data (need to be stable when sampled)
    reg [7:0] spi_data_sync1, spi_data_sync2;

    // Edge detection for SPI clock
    wire spi_clk_rising_edge;

    // Synchronized signals
    wire spi_cs_n_sync;
    wire [7:0] spi_data_sync;

    // Synchronization logic
    always @(posedge clk or negedge resetn) begin
        if (!resetn) begin
            spi_clk_sync1  <= 1'b0;
            spi_clk_sync2  <= 1'b0;
            spi_clk_sync3  <= 1'b0;
            spi_cs_n_sync1 <= 1'b1;  // CS is active low, default high
            spi_cs_n_sync2 <= 1'b1;
            spi_data_sync1 <= 8'b0;
            spi_data_sync2 <= 8'b0;
        end else begin
            // SPI clock synchronizer (3-stage for edge detection)
            spi_clk_sync1 <= spi_clk_in;
            spi_clk_sync2 <= spi_clk_sync1;
            spi_clk_sync3 <= spi_clk_sync2;

            // CS synchronizer
            spi_cs_n_sync1 <= spi_cs_n_in;
            spi_cs_n_sync2 <= spi_cs_n_sync1;

            // Data synchronizer
            spi_data_sync1 <= spi_data_in;
            spi_data_sync2 <= spi_data_sync1;
        end
    end

    // Rising edge detection: was low, now high
    assign spi_clk_rising_edge = (spi_clk_sync2 == 1'b1) && (spi_clk_sync3 == 1'b0);

    // Synchronized outputs
    assign spi_cs_n_sync = spi_cs_n_sync2;
    assign spi_data_sync = spi_data_sync2;

    // =========================================================================
    // Byte Counter - counts 0 to 15 (16 bytes = 128 bits)
    // =========================================================================
    reg [3:0] byte_count;
    wire byte_count_done;

    assign byte_count_done = (byte_count == 4'd15);

    // =========================================================================
    // Shift Register - accumulates received bytes
    // =========================================================================
    reg [127:0] shift_reg;

    // =========================================================================
    // State Machine - Sequential Logic
    // =========================================================================
    always @(posedge clk or negedge resetn) begin
        if (!resetn) begin
            state <= STATE_IDLE;
        end else begin
            state <= state_next;
        end
    end

    // =========================================================================
    // State Machine - Combinational Logic
    // =========================================================================
    always @(*) begin
        state_next = state;

        case (state)
            STATE_IDLE: begin
                // Wait for CS to go low (transfer starting)
                if (!spi_cs_n_sync) begin
                    state_next = STATE_RECEIVING;
                end
            end

            STATE_RECEIVING: begin
                // If CS goes high before complete, abort and go idle
                if (spi_cs_n_sync) begin
                    state_next = STATE_IDLE;
                end
                // Check if we've received all 16 bytes
                else if (byte_count_done && spi_clk_rising_edge) begin
                    state_next = STATE_COMPLETE;
                end
            end

            STATE_COMPLETE: begin
                // Stay in complete for one cycle, then back to idle
                // Wait for CS to go high before accepting new transfer
                if (spi_cs_n_sync) begin
                    state_next = STATE_IDLE;
                end
            end

            default: begin
                state_next = STATE_IDLE;
            end
        endcase
    end

    // =========================================================================
    // Data Reception Logic
    // =========================================================================

    // Track state transitions to pulse rx_valid only once
    reg [1:0] state_prev;
    wire entering_complete;

    always @(posedge clk or negedge resetn) begin
        if (!resetn) begin
            state_prev <= STATE_IDLE;
        end else begin
            state_prev <= state;
        end
    end

    assign entering_complete = (state == STATE_COMPLETE) && (state_prev != STATE_COMPLETE);

    always @(posedge clk or negedge resetn) begin
        if (!resetn) begin
            byte_count <= 4'd0;
            shift_reg  <= 128'd0;
            rx_data    <= 128'd0;
            rx_valid   <= 1'b0;
        end else begin
            // Default: clear rx_valid after one cycle
            rx_valid <= 1'b0;

            case (state)
                STATE_IDLE: begin
                    // Reset counter when idle
                    byte_count <= 4'd0;
                    shift_reg  <= 128'd0;
                end

                STATE_RECEIVING: begin
                    // On rising edge of SPI clock, sample data
                    if (spi_clk_rising_edge) begin
                        // Shift in new byte (little-endian: first byte goes to LSB)
                        // Byte 0 → bits [7:0], Byte 1 → bits [15:8], etc.
                        shift_reg <= {spi_data_sync, shift_reg[127:8]};
                        byte_count <= byte_count + 4'd1;
                    end
                end

                STATE_COMPLETE: begin
                    // Latch the received data and signal valid ONLY on entry
                    if (entering_complete) begin
                        rx_data  <= shift_reg;
                        rx_valid <= 1'b1;
                    end
                    // Reset counter for next transfer
                    byte_count <= 4'd0;
                end

                default: begin
                    byte_count <= 4'd0;
                end
            endcase
        end
    end

    // =========================================================================
    // Output Assignments
    // =========================================================================

    // Busy when receiving
    assign rx_busy = (state == STATE_RECEIVING);

    // IRQ directly mirrors rx_valid (active for one cycle)
    assign irq_rx = rx_valid;

endmodule

tb_spi_slave_8lane.v
/*
 * Testbench for 8-Lane Parallel SPI Slave
 *
 * Simulates an external SPI master sending 128-bit data
 * and verifies the slave receives it correctly.
 */

`timescale 1ns/1ps

module tb_spi_slave_8lane;

    // =========================================================================
    // Clock and Reset
    // =========================================================================
    reg clk;
    reg resetn;

    // System clock: 50 MHz (20 ns period)
    initial clk = 0;
    always #10 clk = ~clk;

    // =========================================================================
    // SPI Master Signals (driven by testbench)
    // =========================================================================
    reg        spi_clk_in;
    reg [7:0]  spi_data_in;
    reg        spi_cs_n_in;

    // =========================================================================
    // SPI Slave Outputs
    // =========================================================================
    wire [127:0] rx_data;
    wire         rx_valid;
    wire         rx_busy;
    wire         irq_rx;

    // =========================================================================
    // DUT Instantiation
    // =========================================================================
    spi_slave_8lane dut (
        .clk         (clk),
        .resetn      (resetn),
        .spi_clk_in  (spi_clk_in),
        .spi_data_in (spi_data_in),
        .spi_cs_n_in (spi_cs_n_in),
        .rx_data     (rx_data),
        .rx_valid    (rx_valid),
        .rx_busy     (rx_busy),
        .irq_rx      (irq_rx)
    );

    // =========================================================================
    // Test Data - FIPS-197 AES Test Vector (Ciphertext)
    // =========================================================================
    // Ciphertext: 0x69c4e0d86a7b0430d8cdb78070b4c55a
    // Sent as 16 bytes, LSB first
    reg [7:0] test_bytes [0:15];

    initial begin
        // Little-endian byte order
        test_bytes[0]  = 8'h5a;  // LSB
        test_bytes[1]  = 8'hc5;
        test_bytes[2]  = 8'hb4;
        test_bytes[3]  = 8'h70;
        test_bytes[4]  = 8'h80;
        test_bytes[5]  = 8'hb7;
        test_bytes[6]  = 8'hcd;
        test_bytes[7]  = 8'hd8;
        test_bytes[8]  = 8'h30;
        test_bytes[9]  = 8'h04;
        test_bytes[10] = 8'h7b;
        test_bytes[11] = 8'h6a;
        test_bytes[12] = 8'hd8;
        test_bytes[13] = 8'he0;
        test_bytes[14] = 8'hc4;
        test_bytes[15] = 8'h69;  // MSB
    end

    // Expected 128-bit result (after reassembly)
    wire [127:0] expected_data = 128'h69c4e0d86a7b0430d8cdb78070b4c55a;

    // =========================================================================
    // SPI Master Task - Send one byte
    // =========================================================================
    task spi_send_byte;
        input [7:0] data;
        begin
            // Setup data
            spi_data_in = data;
            #20;  // Wait 1 system clock

            // Rising edge of SPI clock
            spi_clk_in = 1;
            #40;  // Hold for 2 system clocks

            // Falling edge of SPI clock
            spi_clk_in = 0;
            #40;  // Inter-byte gap
        end
    endtask

    // =========================================================================
    // SPI Master Task - Send 16 bytes (full transfer)
    // =========================================================================
    task spi_send_128bits;
        integer i;
        begin
            $display("[%0t] SPI Master: Starting 128-bit transfer", $time);

            // Assert chip select (active low)
            spi_cs_n_in = 0;
            #40;

            // Send 16 bytes
            for (i = 0; i < 16; i = i + 1) begin
                $display("[%0t] SPI Master: Sending byte[%0d] = 0x%02h", $time, i, test_bytes[i]);
                spi_send_byte(test_bytes[i]);
            end

            // Deassert chip select
            #40;
            spi_cs_n_in = 1;
            $display("[%0t] SPI Master: Transfer complete, CS deasserted", $time);
        end
    endtask

    // =========================================================================
    // Monitor rx_valid
    // =========================================================================
    always @(posedge clk) begin
        if (rx_valid) begin
            $display("[%0t] SPI Slave: rx_valid asserted!", $time);
            $display("[%0t] SPI Slave: Received data = 0x%032h", $time, rx_data);
        end
    end

    // =========================================================================
    // Main Test Sequence
    // =========================================================================
    initial begin
        $dumpfile("tb_spi_slave_8lane.vcd");
        $dumpvars(0, tb_spi_slave_8lane);

        $display("========================================");
        $display("  8-Lane SPI Slave Testbench");
        $display("========================================");

        // Initialize
        resetn      = 0;
        spi_clk_in  = 0;
        spi_data_in = 8'h00;
        spi_cs_n_in = 1;

        // Reset
        #100;
        resetn = 1;
        $display("[%0t] Reset released", $time);
        #100;

        // =====================================================================
        // Test 1: Normal 128-bit transfer
        // =====================================================================
        $display("\n--- Test 1: Normal 128-bit transfer ---");
        spi_send_128bits();

        // Wait for processing
        #200;

        // Verify received data
        if (rx_data == expected_data) begin
            $display("[PASS] Received data matches expected!");
            $display("       Expected: 0x%032h", expected_data);
            $display("       Received: 0x%032h", rx_data);
        end else begin
            $display("[FAIL] Data mismatch!");
            $display("       Expected: 0x%032h", expected_data);
            $display("       Received: 0x%032h", rx_data);
        end

        // =====================================================================
        // Test 2: Second transfer (verify slave resets properly)
        // =====================================================================
        $display("\n--- Test 2: Second transfer (verify reset) ---");
        #200;

        // Modify test data slightly
        test_bytes[0] = 8'hAA;
        test_bytes[15] = 8'hBB;

        spi_send_128bits();
        #200;

        $display("       Received: 0x%032h", rx_data);

        if (rx_data[7:0] == 8'hAA && rx_data[127:120] == 8'hBB) begin
            $display("[PASS] Second transfer received correctly!");
        end else begin
            $display("[FAIL] Second transfer failed!");
        end

        // =====================================================================
        // Test 3: Aborted transfer (CS goes high early)
        // =====================================================================
        $display("\n--- Test 3: Aborted transfer ---");
        #200;

        spi_cs_n_in = 0;
        #40;

        // Send only 4 bytes then abort
        spi_send_byte(8'h11);
        spi_send_byte(8'h22);
        spi_send_byte(8'h33);
        spi_send_byte(8'h44);

        // Abort by raising CS
        spi_cs_n_in = 1;
        $display("[%0t] SPI Master: Aborted transfer", $time);
        #200;

        // Slave should still have previous valid data
        $display("       rx_data after abort: 0x%032h", rx_data);
        $display("[INFO] Slave should retain last valid data");

        // =====================================================================
        // Done
        // =====================================================================
        #500;
        $display("\n========================================");
        $display("  Testbench Complete");
        $display("========================================");
        $finish;
    end

    // Timeout
    initial begin
        #50000;
        $display("[TIMEOUT] Simulation took too long!");
        $finish;
    end

endmodule

tb_spi_slave_8lane.vcd
$date
	Sat Jan 31 23:10:29 2026
$end
$version
	Icarus Verilog
$end
$timescale
	1ps
$end
$scope module tb_spi_slave_8lane $end
$var wire 128 ! expected_data [127:0] $end
$var wire 1 " rx_valid $end
$var wire 128 # rx_data [127:0] $end
$var wire 1 $ rx_busy $end
$var wire 1 % irq_rx $end
$var reg 1 & clk $end
$var reg 1 ' resetn $end
$var reg 1 ( spi_clk_in $end
$var reg 1 ) spi_cs_n_in $end
$var reg 8 * spi_data_in [7:0] $end
$scope module dut $end
$var wire 1 & clk $end
$var wire 1 + entering_complete $end
$var wire 1 % irq_rx $end
$var wire 1 ' resetn $end
$var wire 1 ( spi_clk_in $end
$var wire 1 , spi_clk_rising_edge $end
$var wire 1 ) spi_cs_n_in $end
$var wire 1 - spi_cs_n_sync $end
$var wire 8 . spi_data_in [7:0] $end
$var wire 8 / spi_data_sync [7:0] $end
$var wire 1 $ rx_busy $end
$var wire 1 0 byte_count_done $end
$var parameter 2 1 STATE_COMPLETE $end
$var parameter 2 2 STATE_IDLE $end
$var parameter 2 3 STATE_RECEIVING $end
$var reg 4 4 byte_count [3:0] $end
$var reg 128 5 rx_data [127:0] $end
$var reg 1 " rx_valid $end
$var reg 128 6 shift_reg [127:0] $end
$var reg 1 7 spi_clk_sync1 $end
$var reg 1 8 spi_clk_sync2 $end
$var reg 1 9 spi_clk_sync3 $end
$var reg 1 : spi_cs_n_sync1 $end
$var reg 1 ; spi_cs_n_sync2 $end
$var reg 8 < spi_data_sync1 [7:0] $end
$var reg 8 = spi_data_sync2 [7:0] $end
$var reg 2 > state [1:0] $end
$var reg 2 ? state_next [1:0] $end
$var reg 2 @ state_prev [1:0] $end
$upscope $end
$scope task spi_send_128bits $end
$var integer 32 A i [31:0] $end
$upscope $end
$scope task spi_send_byte $end
$var reg 8 B data [7:0] $end
$upscope $end
$upscope $end
$enddefinitions $end
$comment Show the parameter values. $end
$dumpall
b1 3
b0 2
b10 1
$end
#0
$dumpvars
bx B
bx A
b0 @
b0 ?
b0 >
b0 =
b0 <
1;
1:
09
08
07
b0 6
b0 5
b0 4
00
b0 /
b0 .
1-
0,
0+
b0 *
1)
0(
0'
0&
0%
0$
b0 #
0"
b1101001110001001110000011011000011010100111101100000100001100001101100011001101101101111000000001110000101101001100010101011010 !
$end
#10000
1&
#20000
0&
#30000
1&
#40000
0&
#50000
1&
#60000
0&
#70000
1&
#80000
0&
#90000
1&
#100000
0&
1'
#110000
1&
#120000
0&
#130000
1&
#140000
0&
#150000
1&
#160000
0&
#170000
1&
#180000
0&
#190000
1&
#200000
0&
0)
#210000
0:
1&
#220000
0&
#230000
b1 ?
0-
0;
1&
#240000
0&
b1011010 *
b1011010 .
b1011010 B
b0 A
#250000
1$
b1 >
b1011010 <
1&
#260000
0&
1(
#270000
b1011010 /
b1011010 =
17
b1 @
1&
#280000
0&
#290000
1,
18
1&
#300000
0&
0(
#310000
0,
19
07
b1 4
b1011010000000000000000000000000000000000000000000000000000000000000000000000000000000000000000000000000000000000000000000000000 6
1&
#320000
0&
#330000
08
1&
#340000
0&
b11000101 *
b11000101 .
b11000101 B
b1 A
#350000
b11000101 <
09
1&
#360000
0&
1(
#370000
b11000101 /
b11000101 =
17
1&
#380000
0&
#390000
1,
18
1&
#400000
0&
0(
#410000
0,
b10 4
b11000101010110100000000000000000000000000000000000000000000000000000000000000000000000000000000000000000000000000000000000000000 6
19
07
1&
#420000
0&
#430000
08
1&
#440000
0&
b10110100 *
b10110100 .
b10110100 B
b10 A
#450000
b10110100 <
09
1&
#460000
0&
1(
#470000
b10110100 /
b10110100 =
17
1&
#480000
0&
#490000
1,
18
1&
#500000
0&
0(
#510000
0,
19
07
b11 4
b10110100110001010101101000000000000000000000000000000000000000000000000000000000000000000000000000000000000000000000000000000000 6
1&
#520000
0&
#530000
08
1&
#540000
0&
b1110000 *
b1110000 .
b1110000 B
b11 A
#550000
b1110000 <
09
1&
#560000
0&
1(
#570000
b1110000 /
b1110000 =
17
1&
#580000
0&
#590000
1,
18
1&
#600000
0&
0(
#610000
0,
b100 4
b1110000101101001100010101011010000000000000000000000000000000000000000000000000000000000000000000000000000000000000000000000000 6
19
07
1&
#620000
0&
#630000
08
1&
#640000
0&
b10000000 *
b10000000 .
b10000000 B
b100 A
#650000
b10000000 <
09
1&
#660000
0&
1(
#670000
b10000000 /
b10000000 =
17
1&
#680000
0&
#690000
1,
18
1&
#700000
0&
0(
#710000
0,
19
07
b101 4
b10000000011100001011010011000101010110100000000000000000000000000000000000000000000000000000000000000000000000000000000000000000 6
1&
#720000
0&
#730000
08
1&
#740000
0&
b10110111 *
b10110111 .
b10110111 B
b101 A
#750000
b10110111 <
09
1&
#760000
0&
1(
#770000
b10110111 /
b10110111 =
17
1&
#780000
0&
#790000
1,
18
1&
#800000
0&
0(
#810000
0,
b110 4
b10110111100000000111000010110100110001010101101000000000000000000000000000000000000000000000000000000000000000000000000000000000 6
19
07
1&
#820000
0&
#830000
08
1&
#840000
0&
b11001101 *
b11001101 .
b11001101 B
b110 A
#850000
b11001101 <
09
1&
#860000
0&
1(
#870000
b11001101 /
b11001101 =
17
1&
#880000
0&
#890000
1,
18
1&
#900000
0&
0(
#910000
0,
19
07
b111 4
b11001101101101111000000001110000101101001100010101011010000000000000000000000000000000000000000000000000000000000000000000000000 6
1&
#920000
0&
#930000
08
1&
#940000
0&
b11011000 *
b11011000 .
b11011000 B
b111 A
#950000
b11011000 <
09
1&
#960000
0&
1(
#970000
b11011000 /
b11011000 =
17
1&
#980000
0&
#990000
1,
18
1&
#1000000
0&
0(
#1010000
0,
b1000 4
b11011000110011011011011110000000011100001011010011000101010110100000000000000000000000000000000000000000000000000000000000000000 6
19
07
1&
#1020000
0&
#1030000
08
1&
#1040000
0&
b110000 *
b110000 .
b110000 B
b1000 A
#1050000
b110000 <
09
1&
#1060000
0&
1(
#1070000
b110000 /
b110000 =
17
1&
#1080000
0&
#1090000
1,
18
1&
#1100000
0&
0(
#1110000
0,
19
07
b1001 4
b110000110110001100110110110111100000000111000010110100110001010101101000000000000000000000000000000000000000000000000000000000 6
1&
#1120000
0&
#1130000
08
1&
#1140000
0&
b100 *
b100 .
b100 B
b1001 A
#1150000
b100 <
09
1&
#1160000
0&
1(
#1170000
b100 /
b100 =
17
1&
#1180000
0&
#1190000
1,
18
1&
#1200000
0&
0(
#1210000
0,
b1010 4
b100001100001101100011001101101101111000000001110000101101001100010101011010000000000000000000000000000000000000000000000000 6
19
07
1&
#1220000
0&
#1230000
08
1&
#1240000
0&
b1111011 *
b1111011 .
b1111011 B
b1010 A
#1250000
b1111011 <
09
1&
#1260000
0&
1(
#1270000
b1111011 /
b1111011 =
17
1&
#1280000
0&
#1290000
1,
18
1&
#1300000
0&
0(
#1310000
0,
19
07
b1011 4
b1111011000001000011000011011000110011011011011110000000011100001011010011000101010110100000000000000000000000000000000000000000 6
1&
#1320000
0&
#1330000
08
1&
#1340000
0&
b1101010 *
b1101010 .
b1101010 B
b1011 A
#1350000
b1101010 <
09
1&
#1360000
0&
1(
#1370000
b1101010 /
b1101010 =
17
1&
#1380000
0&
#1390000
1,
18
1&
#1400000
0&
0(
#1410000
0,
b1100 4
b1101010011110110000010000110000110110001100110110110111100000000111000010110100110001010101101000000000000000000000000000000000 6
19
07
1&
#1420000
0&
#1430000
08
1&
#1440000
0&
b11011000 *
b11011000 .
b11011000 B
b1100 A
#1450000
b11011000 <
09
1&
#1460000
0&
1(
#1470000
b11011000 /
b11011000 =
17
1&
#1480000
0&
#1490000
1,
18
1&
#1500000
0&
0(
#1510000
0,
19
07
b1101 4
b11011000011010100111101100000100001100001101100011001101101101111000000001110000101101001100010101011010000000000000000000000000 6
1&
#1520000
0&
#1530000
08
1&
#1540000
0&
b11100000 *
b11100000 .
b11100000 B
b1101 A
#1550000
b11100000 <
09
1&
#1560000
0&
1(
#1570000
b11100000 /
b11100000 =
17
1&
#1580000
0&
#1590000
1,
18
1&
#1600000
0&
0(
#1610000
0,
b1110 4
b11100000110110000110101001111011000001000011000011011000110011011011011110000000011100001011010011000101010110100000000000000000 6
19
07
1&
#1620000
0&
#1630000
08
1&
#1640000
0&
b11000100 *
b11000100 .
b11000100 B
b1110 A
#1650000
b11000100 <
09
1&
#1660000
0&
1(
#1670000
b11000100 /
b11000100 =
17
1&
#1680000
0&
#1690000
1,
18
1&
#1700000
0&
0(
#1710000
0,
b1 ?
19
07
10
b1111 4
b11000100111000001101100001101010011110110000010000110000110110001100110110110111100000000111000010110100110001010101101000000000 6
1&
#1720000
0&
#1730000
08
1&
#1740000
0&
b1101001 *
b1101001 .
b1101001 B
b1111 A
#1750000
b1101001 <
09
1&
#1760000
0&
1(
#1770000
b1101001 /
b1101001 =
17
1&
#1780000
0&
#1790000
b10 ?
1,
18
1&
#1800000
0&
0(
#1810000
0,
1+
00
b0 4
b1101001110001001110000011011000011010100111101100000100001100001101100011001101101101111000000001110000101101001100010101011010 6
0$
b10 >
19
07
1&
#1820000
0&
#1830000
0+
08
b10 @
1%
1"
b1101001110001001110000011011000011010100111101100000100001100001101100011001101101101111000000001110000101101001100010101011010 #
b1101001110001001110000011011000011010100111101100000100001100001101100011001101101101111000000001110000101101001100010101011010 5
1&
#1840000
0&
b10000 A
#1850000
0%
0"
09
1&
#1860000
0&
#1870000
1&
#1880000
0&
1)
#1890000
1:
1&
#1900000
0&
#1910000
b0 ?
1-
1;
1&
#1920000
0&
#1930000
b0 >
1&
#1940000
0&
#1950000
b0 @
b0 6
1&
#1960000
0&
#1970000
1&
#1980000
0&
#1990000
1&
#2000000
0&
#2010000
1&
#2020000
0&
#2030000
1&
#2040000
0&
#2050000
1&
#2060000
0&
#2070000
1&
#2080000
0&
#2090000
1&
#2100000
0&
#2110000
1&
#2120000
0&
#2130000
1&
#2140000
0&
#2150000
1&
#2160000
0&
#2170000
1&
#2180000
0&
#2190000
1&
#2200000
0&
#2210000
1&
#2220000
0&
#2230000
1&
#2240000
0&
#2250000
1&
#2260000
0&
#2270000
1&
#2280000
0&
0)
#2290000
0:
1&
#2300000
0&
#2310000
b1 ?
0-
0;
1&
#2320000
0&
b10101010 *
b10101010 .
b10101010 B
b0 A
#2330000
1$
b1 >
b10101010 <
1&
#2340000
0&
1(
#2350000
b10101010 /
b10101010 =
17
b1 @
1&
#2360000
0&
#2370000
1,
18
1&
#2380000
0&
0(
#2390000
0,
19
07
b1 4
b10101010000000000000000000000000000000000000000000000000000000000000000000000000000000000000000000000000000000000000000000000000 6
1&
#2400000
0&
#2410000
08
1&
#2420000
0&
b11000101 *
b11000101 .
b11000101 B
b1 A
#2430000
b11000101 <
09
1&
#2440000
0&
1(
#2450000
b11000101 /
b11000101 =
17
1&
#2460000
0&
#2470000
1,
18
1&
#2480000
0&
0(
#2490000
0,
b10 4
b11000101101010100000000000000000000000000000000000000000000000000000000000000000000000000000000000000000000000000000000000000000 6
19
07
1&
#2500000
0&
#2510000
08
1&
#2520000
0&
b10110100 *
b10110100 .
b10110100 B
b10 A
#2530000
b10110100 <
09
1&
#2540000
0&
1(
#2550000
b10110100 /
b10110100 =
17
1&
#2560000
0&
#2570000
1,
18
1&
#2580000
0&
0(
#2590000
0,
19
07
b11 4
b10110100110001011010101000000000000000000000000000000000000000000000000000000000000000000000000000000000000000000000000000000000 6
1&
#2600000
0&
#2610000
08
1&
#2620000
0&
b1110000 *
b1110000 .
b1110000 B
b11 A
#2630000
b1110000 <
09
1&
#2640000
0&
1(
#2650000
b1110000 /
b1110000 =
17
1&
#2660000
0&
#2670000
1,
18
1&
#2680000
0&
0(
#2690000
0,
b100 4
b1110000101101001100010110101010000000000000000000000000000000000000000000000000000000000000000000000000000000000000000000000000 6
19
07
1&
#2700000
0&
#2710000
08
1&
#2720000
0&
b10000000 *
b10000000 .
b10000000 B
b100 A
#2730000
b10000000 <
09
1&
#2740000
0&
1(
#2750000
b10000000 /
b10000000 =
17
1&
#2760000
0&
#2770000
1,
18
1&
#2780000
0&
0(
#2790000
0,
19
07
b101 4
b10000000011100001011010011000101101010100000000000000000000000000000000000000000000000000000000000000000000000000000000000000000 6
1&
#2800000
0&
#2810000
08
1&
#2820000
0&
b10110111 *
b10110111 .
b10110111 B
b101 A
#2830000
b10110111 <
09
1&
#2840000
0&
1(
#2850000
b10110111 /
b10110111 =
17
1&
#2860000
0&
#2870000
1,
18
1&
#2880000
0&
0(
#2890000
0,
b110 4
b10110111100000000111000010110100110001011010101000000000000000000000000000000000000000000000000000000000000000000000000000000000 6
19
07
1&
#2900000
0&
#2910000
08
1&
#2920000
0&
b11001101 *
b11001101 .
b11001101 B
b110 A
#2930000
b11001101 <
09
1&
#2940000
0&
1(
#2950000
b11001101 /
b11001101 =
17
1&
#2960000
0&
#2970000
1,
18
1&
#2980000
0&
0(
#2990000
0,
19
07
b111 4
b11001101101101111000000001110000101101001100010110101010000000000000000000000000000000000000000000000000000000000000000000000000 6
1&
#3000000
0&
#3010000
08
1&
#3020000
0&
b11011000 *
b11011000 .
b11011000 B
b111 A
#3030000
b11011000 <
09
1&
#3040000
0&
1(
#3050000
b11011000 /
b11011000 =
17
1&
#3060000
0&
#3070000
1,
18
1&
#3080000
0&
0(
#3090000
0,
b1000 4
b11011000110011011011011110000000011100001011010011000101101010100000000000000000000000000000000000000000000000000000000000000000 6
19
07
1&
#3100000
0&
#3110000
08
1&
#3120000
0&
b110000 *
b110000 .
b110000 B
b1000 A
#3130000
b110000 <
09
1&
#3140000
0&
1(
#3150000
b110000 /
b110000 =
17
1&
#3160000
0&
#3170000
1,
18
1&
#3180000
0&
0(
#3190000
0,
19
07
b1001 4
b110000110110001100110110110111100000000111000010110100110001011010101000000000000000000000000000000000000000000000000000000000 6
1&
#3200000
0&
#3210000
08
1&
#3220000
0&
b100 *
b100 .
b100 B
b1001 A
#3230000
b100 <
09
1&
#3240000
0&
1(
#3250000
b100 /
b100 =
17
1&
#3260000
0&
#3270000
1,
18
1&
#3280000
0&
0(
#3290000
0,
b1010 4
b100001100001101100011001101101101111000000001110000101101001100010110101010000000000000000000000000000000000000000000000000 6
19
07
1&
#3300000
0&
#3310000
08
1&
#3320000
0&
b1111011 *
b1111011 .
b1111011 B
b1010 A
#3330000
b1111011 <
09
1&
#3340000
0&
1(
#3350000
b1111011 /
b1111011 =
17
1&
#3360000
0&
#3370000
1,
18
1&
#3380000
0&
0(
#3390000
0,
19
07
b1011 4
b1111011000001000011000011011000110011011011011110000000011100001011010011000101101010100000000000000000000000000000000000000000 6
1&
#3400000
0&
#3410000
08
1&
#3420000
0&
b1101010 *
b1101010 .
b1101010 B
b1011 A
#3430000
b1101010 <
09
1&
#3440000
0&
1(
#3450000
b1101010 /
b1101010 =
17
1&
#3460000
0&
#3470000
1,
18
1&
#3480000
0&
0(
#3490000
0,
b1100 4
b1101010011110110000010000110000110110001100110110110111100000000111000010110100110001011010101000000000000000000000000000000000 6
19
07
1&
#3500000
0&
#3510000
08
1&
#3520000
0&
b11011000 *
b11011000 .
b11011000 B
b1100 A
#3530000
b11011000 <
09
1&
#3540000
0&
1(
#3550000
b11011000 /
b11011000 =
17
1&
#3560000
0&
#3570000
1,
18
1&
#3580000
0&
0(
#3590000
0,
19
07
b1101 4
b11011000011010100111101100000100001100001101100011001101101101111000000001110000101101001100010110101010000000000000000000000000 6
1&
#3600000
0&
#3610000
08
1&
#3620000
0&
b11100000 *
b11100000 .
b11100000 B
b1101 A
#3630000
b11100000 <
09
1&
#3640000
0&
1(
#3650000
b11100000 /
b11100000 =
17
1&
#3660000
0&
#3670000
1,
18
1&
#3680000
0&
0(
#3690000
0,
b1110 4
b11100000110110000110101001111011000001000011000011011000110011011011011110000000011100001011010011000101101010100000000000000000 6
19
07
1&
#3700000
0&
#3710000
08
1&
#3720000
0&
b11000100 *
b11000100 .
b11000100 B
b1110 A
#3730000
b11000100 <
09
1&
#3740000
0&
1(
#3750000
b11000100 /
b11000100 =
17
1&
#3760000
0&
#3770000
1,
18
1&
#3780000
0&
0(
#3790000
0,
b1 ?
19
07
10
b1111 4
b11000100111000001101100001101010011110110000010000110000110110001100110110110111100000000111000010110100110001011010101000000000 6
1&
#3800000
0&
#3810000
08
1&
#3820000
0&
b10111011 *
b10111011 .
b10111011 B
b1111 A
#3830000
b10111011 <
09
1&
#3840000
0&
1(
#3850000
b10111011 /
b10111011 =
17
1&
#3860000
0&
#3870000
b10 ?
1,
18
1&
#3880000
0&
0(
#3890000
0,
1+
00
b0 4
b10111011110001001110000011011000011010100111101100000100001100001101100011001101101101111000000001110000101101001100010110101010 6
0$
b10 >
19
07
1&
#3900000
0&
#3910000
0+
08
b10 @
1%
1"
b10111011110001001110000011011000011010100111101100000100001100001101100011001101101101111000000001110000101101001100010110101010 #
b10111011110001001110000011011000011010100111101100000100001100001101100011001101101101111000000001110000101101001100010110101010 5
1&
#3920000
0&
b10000 A
#3930000
0%
0"
09
1&
#3940000
0&
#3950000
1&
#3960000
0&
1)
#3970000
1:
1&
#3980000
0&
#3990000
b0 ?
1-
1;
1&
#4000000
0&
#4010000
b0 >
1&
#4020000
0&
#4030000
b0 @
b0 6
1&
#4040000
0&
#4050000
1&
#4060000
0&
#4070000
1&
#4080000
0&
#4090000
1&
#4100000
0&
#4110000
1&
#4120000
0&
#4130000
1&
#4140000
0&
#4150000
1&
#4160000
0&
#4170000
1&
#4180000
0&
#4190000
1&
#4200000
0&
#4210000
1&
#4220000
0&
#4230000
1&
#4240000
0&
#4250000
1&
#4260000
0&
#4270000
1&
#4280000
0&
#4290000
1&
#4300000
0&
#4310000
1&
#4320000
0&
#4330000
1&
#4340000
0&
#4350000
1&
#4360000
0&
0)
#4370000
0:
1&
#4380000
0&
#4390000
b1 ?
0-
0;
1&
#4400000
0&
b10001 *
b10001 .
b10001 B
#4410000
1$
b1 >
b10001 <
1&
#4420000
0&
1(
#4430000
b10001 /
b10001 =
17
b1 @
1&
#4440000
0&
#4450000
1,
18
1&
#4460000
0&
0(
#4470000
0,
19
07
b1 4
b10001000000000000000000000000000000000000000000000000000000000000000000000000000000000000000000000000000000000000000000000000 6
1&
#4480000
0&
#4490000
08
1&
#4500000
0&
b100010 *
b100010 .
b100010 B
#4510000
b100010 <
09
1&
#4520000
0&
1(
#4530000
b100010 /
b100010 =
17
1&
#4540000
0&
#4550000
1,
18
1&
#4560000
0&
0(
#4570000
0,
b10 4
b100010000100010000000000000000000000000000000000000000000000000000000000000000000000000000000000000000000000000000000000000000 6
19
07
1&
#4580000
0&
#4590000
08
1&
#4600000
0&
b110011 *
b110011 .
b110011 B
